Metadata-Version: 2.4
Name: adafruit-circuitpython-dang
Version: 1.0.1
Summary: A subset of the curses framework. Used for making terminal based applications.
Author-email: Adafruit Industries <circuitpython@adafruit.com>
License: MIT
Project-URL: Homepage, https://github.com/adafruit/Adafruit_CircuitPython_Dang
Keywords: adafruit,blinka,circuitpython,micropython,dang,curses,terminal,ascii,ansi,tui
Classifier: Intended Audience :: Developers
Classifier: Topic :: Software Development :: Libraries
Classifier: Topic :: Software Development :: Embedded Systems
Classifier: Topic :: System :: Hardware
Classifier: License :: OSI Approved :: MIT License
Classifier: Programming Language :: Python :: 3
License-File: LICENSE
Requires-Dist: Adafruit-Blinka
Provides-Extra: optional
Dynamic: license-file
